AUTHORS
Changelog.txt
LICENSE
MANIFEST.in
README.md
setup.py
negar/__init__.py
negar/constants.py
negar/gui.py
negar/virastar.py
negar/data/immutable.words
python_negar.egg-info/PKG-INFO
python_negar.egg-info/SOURCES.txt
python_negar.egg-info/dependency_links.txt
python_negar.egg-info/entry_points.txt
python_negar.egg-info/requires.txt
python_negar.egg-info/top_level.txt
tests/test_unittest.py