Metadata-Version: 2.1
Name: python-negar
Version: 1.4.2
Summary: Negar is a spell corrector and Persian text editor
Home-page: http://github.com/shahinism/python-negar
Author: Shahin Azad
Author-email: ishahinism@gmail.com
Maintainer: Javad Razavian, Alireza Savand
Maintainer-email: javadr@gmail.com, alireza.savand@gmail.com
License: GPL
Keywords: spellcheck Persian editor
Classifier: Environment :: Console
Classifier: License :: OSI Approved :: GNU General Public License v3 (GPLv3)
Classifier: Programming Language :: Python
Classifier: Programming Language :: Python :: 3
Requires-Python: >=3.8
License-File: LICENSE
License-File: AUTHORS
Requires-Dist: regex
